ashendb/__init__.py
ashendb/client.py
ashendb/collection.py
ashendb/database.py
ashendb/document.py
ashendb/exception.py
ashendb/helper.py
AshenDB-0.0.8.dist-info/LICENSE
AshenDB-0.0.8.dist-info/METADATA
AshenDB-0.0.8.dist-info/WHEEL
AshenDB-0.0.8.dist-info/entry_points.txt
AshenDB-0.0.8.dist-info/top_level.txt
AshenDB-0.0.8.dist-info/RECORD
