Metadata-Version: 2.1
Name: AshenDB
Version: 0.0.8
Summary: Another stupid library for using json as Database
Author-email: Abdullah Al Muaz <abdullahalmuaz15@gmail.com>
License: MIT License
Project-URL: Homepage, https://github.com/aurkaxi/AshenDB
Project-URL: Documentation, https://ashendb.rtfd.io
Keywords: json,mongodb,database,embedded-database,serverless
Classifier: Development Status :: 3 - Alpha
Classifier: License :: OSI Approved :: MIT License
Classifier: Intended Audience :: Developers
Classifier: Natural Language :: English
Classifier: Operating System :: OS Independent
Classifier: Programming Language :: Python :: 3.10
Requires-Python: >=3.10
License-File: LICENSE
Requires-Dist: aiofiles
